gjson/__init__.py
gjson/_cli.py
gjson/_gjson.py
gjson/_protocols.py
gjson/exceptions.py
gjson/py.typed
gjson-1.0.0.dist-info/LICENSE
gjson-1.0.0.dist-info/METADATA
gjson-1.0.0.dist-info/WHEEL
gjson-1.0.0.dist-info/entry_points.txt
gjson-1.0.0.dist-info/top_level.txt
gjson-1.0.0.dist-info/RECORD
