Metadata-Version: 2.1
Name: gjson
Version: 1.0.0
Summary: gjson-py is a Python package that provides a simple way to filter and extract data from JSON-like objects or JSON files, using the GJSON syntax.
Home-page: https://github.com/volans-/gjson-py
Author: Riccardo Coccioli
Author-email: volans-@users.noreply.github.com
License: GPLv3+
Keywords: gjson,json
Platform: GNU/Linux
Platform: BSD
Platform: MacOSX
Classifier: Development Status :: 5 - Production/Stable
Classifier: Environment :: Console
Classifier: Intended Audience :: Developers
Classifier: Intended Audience :: End Users/Desktop
Classifier: Intended Audience :: Information Technology
Classifier: Intended Audience :: Science/Research
Classifier: Intended Audience :: System Administrators
Classifier: License :: OSI Approved :: GNU General Public License v3 or later (GPLv3+)
Classifier: Operating System :: OS Independent
Classifier: Programming Language :: Python :: 3.9
Classifier: Programming Language :: Python :: 3.10
Classifier: Programming Language :: Python :: 3.11
Classifier: Programming Language :: Python :: 3 :: Only
Classifier: Topic :: Software Development :: Libraries :: Python Modules
Classifier: Topic :: Text Processing
Classifier: Topic :: Utilities
Classifier: Typing :: Typed
Requires-Python: >=3.9
License-File: LICENSE
Provides-Extra: prospector
Requires-Dist: prospector[with_everything] ; extra == 'prospector'
Requires-Dist: pytest ; extra == 'prospector'
Provides-Extra: tests
Requires-Dist: bandit ; extra == 'tests'
Requires-Dist: flake8 ; extra == 'tests'
Requires-Dist: flake8-import-order ; extra == 'tests'
Requires-Dist: mypy ; extra == 'tests'
Requires-Dist: pytest-cov ; extra == 'tests'
Requires-Dist: pytest-xdist ; extra == 'tests'
Requires-Dist: pytest ; extra == 'tests'
Requires-Dist: sphinx-rtd-theme ; extra == 'tests'
Requires-Dist: sphinx-argparse ; extra == 'tests'
Requires-Dist: sphinx-autodoc-typehints ; extra == 'tests'
Requires-Dist: Sphinx ; extra == 'tests'
Requires-Dist: types-pkg-resources ; extra == 'tests'
